PathFindy/PathFindy.py
PathFindy/__init__.py
pathfindy-0.1.0.dist-info/licenses/LICENSE
pathfindy-0.1.0.dist-info/METADATA
pathfindy-0.1.0.dist-info/WHEEL
pathfindy-0.1.0.dist-info/top_level.txt
pathfindy-0.1.0.dist-info/RECORD
