Metadata-Version: 2.4
Name: PathFindy
Version: 0.1.0
Summary: An autonomous vehicle platform by Pathfinder
Author-email: Pathfinder Team <contact@pathfinder.ai>
License: MIT
Project-URL: Homepage, https://github.com/Comrid/Pathfindy
Project-URL: Bug Tracker, https://github.com/Comrid/Pathfindy/issues
Classifier: Programming Language :: Python :: 3
Classifier: License :: OSI Approved :: MIT License
Classifier: Operating System :: OS Independent
Requires-Python: >=3.7
License-File: LICENSE
Dynamic: license-file
